pipup.py
requp-1.2.1.dist-info/licenses/LICENSE
requp-1.2.1.dist-info/METADATA
requp-1.2.1.dist-info/WHEEL
requp-1.2.1.dist-info/entry_points.txt
requp-1.2.1.dist-info/top_level.txt
requp-1.2.1.dist-info/RECORD
