Metadata-Version: 2.4
Name: requp
Version: 1.2.1
Summary: Update Python package versions in requirements.txt with exact versions from pip freeze
Home-page: https://github.com/abozaralizadeh/pipup
Author: Abozar Alizadeh
Author-email: abozar@example.com
Project-URL: Bug Reports, https://github.com/abozaralizadeh/pipup/issues
Project-URL: Source, https://github.com/abozaralizadeh/pipup
Keywords: pip requirements version management python packaging
Classifier: Development Status :: 5 - Production/Stable
Classifier: Intended Audience :: Developers
Classifier: License :: OSI Approved :: MIT License
Classifier: Operating System :: OS Independent
Classifier: Programming Language :: Python :: 3
Classifier: Programming Language :: Python :: 3.7
Classifier: Programming Language :: Python :: 3.8
Classifier: Programming Language :: Python :: 3.9
Classifier: Programming Language :: Python :: 3.10
Classifier: Programming Language :: Python :: 3.11
Classifier: Programming Language :: Python :: 3.12
Classifier: Topic :: Software Development :: Build Tools
Classifier: Topic :: System :: Archiving :: Packaging
Requires-Python: >=3.7
License-File: LICENSE
Dynamic: author
Dynamic: author-email
Dynamic: classifier
Dynamic: description
Dynamic: description-content-type
Dynamic: home-page
Dynamic: keywords
Dynamic: license-file
Dynamic: project-url
Dynamic: requires-python
Dynamic: summary
